[
  {
    "id": 1,
    "evento": "Agrocomercial Kist e Hemann",
    "data": "28/05/2026",
    "horario": "08:30",
    "local": "Agrocomercial Kist e Hemann - Unidade Santa Cruz do Sul",
    "anfitriao": "Diretoria",
    "assunto": "Demonstração Dante Safra",
    "observacoes": "Confirmado",
    "status": "Confirmado",
    "desfecho": "Em Aberto"
  },
  {
    "id": 2,
    "evento": "Apresentação Cidades do Futuro",
    "data": "28/05/2026",
    "horario": "13:30",
    "local": "Prefeitura de passo do Sobrado, RS",
    "anfitriao": "Prefeito, sec. da agricultura, saúde e educação.",
    "assunto": "Apresentação do ecossistema e ferramentas de saúde",
    "observacoes": "Confirmado",
    "status": "Confirmado",
    "desfecho": "Em Aberto"
  },
  {
    "id": 3,
    "evento": "Apresentação Cidades do futuro",
    "data": "28/05/2026",
    "horario": "14:30",
    "local": "Prefeitura de Vale Verde, RS",
    "anfitriao": "Prefeito, sec. da agricultura, saúde e educação",
    "assunto": "Pilar Educação - Retenção de Jovens",
    "observacoes": "Confirmado",
    "status": "Confirmado",
    "desfecho": "Em Aberto"
  },
  {
    "id": 4,
    "evento": "Apresentação Cidades do futuro",
    "data": "29/05/2026",
    "horario": "13:30",
    "local": "Prefeitura de Ipê",
    "anfitriao": "Prefeito, sec. agricultura, educação e saúde",
    "assunto": "Apresentação cidades do futuro.",
    "observacoes": "Confirmado",
    "status": "Confirmado",
    "desfecho": "Em Aberto"
  },
  {
    "id": 5,
    "evento": "Apresentação Cidades do futuro",
    "data": "01/06/2026",
    "horario": "09:00",
    "local": "Prefeitura de Vanini",
    "anfitriao": "Prefeito, sec. da gricultura, educação e saúde.",
    "assunto": "Apresentação do ecossistema",
    "observacoes": "Confirmado",
    "status": "Confirmado",
    "desfecho": "Em Aberto"
  },
  {
    "id": 1784823375217,
    "evento": "Prefeito de Taquari — Reunião Estratégica",
    "data": "24/07/2026",
    "horario": "09:00",
    "local": "https://nexustreinamento.com/gabinete/meet?room=room-ww1obtn&join=true",
    "anfitriao": "Geanderson Leandro Schuh",
    "assunto": "Vitrine inovadora.",
    "observacoes": "Agendamento automático via portal. E-mail: geanderson@nexustreinamento.com | WhatsApp: 51999799582",
    "status": "Confirmado",
    "desfecho": "Em Aberto"
  },
  {
    "id": 1784823495475,
    "evento": "Prefeito de Taquari — Reunião Estratégica",
    "data": "24/07/2026",
    "horario": "09:00",
    "local": "https://nexustreinamento.com/gabinete/meet?room=room-tk4599i&join=true",
    "anfitriao": "Geanderson Leandro Schuh",
    "assunto": "Vitrine inovadora.",
    "observacoes": "Agendamento automático via portal. E-mail: geanderson@nexustreinamento.com | WhatsApp: 51999799582",
    "status": "Confirmado",
    "desfecho": "Em Aberto"
  },
  {
    "id": 1784824331435,
    "evento": "Secretaria de Turismo de Sao Paulo — Reunião Estratégica",
    "data": "24/07/2026",
    "horario": "09:00",
    "local": "https://nexustreinamento.com/gabinete/meet?room=room-lmfbc5x&join=true",
    "anfitriao": "Secretario de Turismo",
    "assunto": "Demonstração de Soluções Soberanas",
    "observacoes": "Agendamento automático via portal. E-mail: turismo@sp.gov.br | WhatsApp: 11999998888",
    "status": "Confirmado",
    "desfecho": "Em Aberto"
  },
  {
    "id": 1784830065445,
    "evento": "Prefeitura Municipal de Urubici — Reunião Estratégica",
    "data": "27/07/2026",
    "horario": "10:00",
    "local": "https://nexustreinamento.com/gabinete/meet?room=room-2law05o&join=true",
    "anfitriao": "Dáfhnne Rocha",
    "assunto": "Inovação no Turismo de Urubici: Inteligência Artificial e Fortalecimento do Comércio Local",
    "observacoes": "Agendamento automático via portal. E-mail: ger.turismo@urubici.sc.gov.br | WhatsApp: Não Informado",
    "status": "Confirmado",
    "desfecho": "Em Aberto"
  },
  {
    "id": 1784825450974,
    "evento": "Guarda Civil Metropolitana de Goiânia — Reunião Estratégica",
    "data": "05/08/2026",
    "horario": "09:00",
    "local": "https://nexustreinamento.com/gabinete/meet?room=room-zvk0xd1&join=true",
    "anfitriao": "Gustavo Toledo da Silva Lima",
    "assunto": "Monitoramento Preditivo e Tecnologia para a Guarda Civil Metropolitana de Goiânia",
    "observacoes": "Agendamento automático via portal. E-mail: geanderson@nexustreinamento.com | WhatsApp: 51999799582",
    "status": "Confirmado",
    "desfecho": "Em Aberto"
  },
  {
    "id": 1784825977918,
    "evento": "Diretor Nexus — Reunião Estratégica",
    "data": "05/08/2026",
    "horario": "10:00",
    "local": "https://nexustreinamento.com/gabinete/meet?room=room-lh9oi2n&join=true",
    "anfitriao": "Geanderson Leandro Schuh",
    "assunto": "Embaixadora Virtual",
    "observacoes": "Agendamento automático via portal. E-mail: geanderson@nexustreinamento.com | WhatsApp: 51 999799582",
    "status": "Confirmado",
    "desfecho": "Em Aberto"
  }
]